LICENSE
MANIFEST.in
README.md
setup.py
django_eveonline_connector/__init__.py
django_eveonline_connector/admin.py
django_eveonline_connector/apps.py
django_eveonline_connector/bindings.py
django_eveonline_connector/decorators.py
django_eveonline_connector/exceptions.py
django_eveonline_connector/forms.py
django_eveonline_connector/models.py
django_eveonline_connector/setup.py
django_eveonline_connector/signals.py
django_eveonline_connector/tasks.py
django_eveonline_connector/urls.py
django_eveonline_connector.egg-info/PKG-INFO
django_eveonline_connector.egg-info/SOURCES.txt
django_eveonline_connector.egg-info/dependency_links.txt
django_eveonline_connector.egg-info/requires.txt
django_eveonline_connector.egg-info/top_level.txt
django_eveonline_connector/fixtures/initial_scopes.json
django_eveonline_connector/migrations/0001_initial.py
django_eveonline_connector/migrations/0002_evetoken_primary.py
django_eveonline_connector/migrations/0003_auto_20190903_2005.py
django_eveonline_connector/migrations/0004_remove_eveclient_esi_scopes.py
django_eveonline_connector/migrations/0005_auto_20191003_1947.py
django_eveonline_connector/migrations/0006_auto_20191003_2008.py
django_eveonline_connector/migrations/0007_auto_20191210_1430.py
django_eveonline_connector/migrations/0008_auto_20191210_1449.py
django_eveonline_connector/migrations/0009_auto_20191210_1538.py
django_eveonline_connector/migrations/0010_auto_20191211_1514.py
django_eveonline_connector/migrations/0011_auto_20191211_1624.py
django_eveonline_connector/migrations/0012_auto_20200225_1921.py
django_eveonline_connector/migrations/0013_evetokentype_description.py
django_eveonline_connector/migrations/0014_load_intial_data.py
django_eveonline_connector/migrations/0015_merge_20200226_1503.py
django_eveonline_connector/migrations/0016_auto_20200226_1730.py
django_eveonline_connector/migrations/0017_primaryevecharacterassociation.py
django_eveonline_connector/migrations/0018_remove_evetoken_primary.py
django_eveonline_connector/migrations/0019_eveasset.py
django_eveonline_connector/migrations/0020_auto_20200227_2151.py
django_eveonline_connector/migrations/0021_auto_20200227_2343.py
django_eveonline_connector/migrations/0022_auto_20200303_1841.py
