Metadata-Version: 2.1
Name: django-eveonline-connector
Version: 1.2.2
Summary: EVE Online integration for SSO, characters, corporations, alliances, and their respective data.
Home-page: https://github.com/KryptedGaming/django-eveonline-connector
Author: porowns
Author-email: porowns@gmail.com
License: MIT License
Platform: UNKNOWN
Classifier: Environment :: Web Environment
Classifier: Framework :: Django
Classifier: Intended Audience :: Developers
Classifier: License :: OSI Approved :: MIT License
Classifier: Operating System :: OS Independent
Classifier: Programming Language :: Python
Classifier: Programming Language :: Python :: 3.5
Classifier: Programming Language :: Python :: 3.6
Classifier: Topic :: Internet :: WWW/HTTP
Classifier: Topic :: Internet :: WWW/HTTP :: Dynamic Content
Provides-Extra: test
